<?xml version="1.0" encoding="utf-8"?>
<!DOCTYPE hibernate-mapping PUBLIC "-//Hibernate/Hibernate Mapping DTD 3.0//EN"
"http://hibernate.sourceforge.net/hibernate-mapping-3.0.dtd">
<!-- 
    Mapping file autogenerated by MyEclipse Persistence Tools
-->
<hibernate-mapping>
    <class name="org.tbcc.entity.TbccBranchType" table="TbccBranchType" schema="dbo" >
            
         <id name="branchId" type="java.lang.Long">
                <column name="BranchID"  />
                <generator class="native"></generator>
         </id>
  
        <property name="branchType" type="java.lang.Integer">
            <column name="BranchType" not-null="true" />
        </property>
        
        <property name="branchName" type="java.lang.String">
            <column name="BranchName" length="100" not-null="true" />
        </property>
        
        <property name="branchCode" type="java.lang.String">
            <column name="BranchCode" length="50" not-null="true" />
        </property>
        
        <property name="branchRelInfo" type="java.lang.String">
            <column name="BranchRelInfo" length="200" />
        </property>
        
        <property name="branchNote" type="java.lang.String">
            <column name="BranchNote" length="200" />
        </property>
        
        <!-- 配置机构的、总部、区域、项目的关联关系 -->
        
        <set name="hqTypes" table="TbccHqBranchRelation" fetch="join">
        	<key column="BranchID"></key>
        	<many-to-many class="org.tbcc.entity.TbccHqType" column="HqID"></many-to-many>
        </set>
        
        <set name="areaTypes" table="TbccAreaBranchRelation">
        	<key column="BranchID"></key>
        	<many-to-many class="org.tbcc.entity.TbccAreaType" column="AreaID"></many-to-many>
        </set>
        
        <set name="prjTypes" table="TbccBranchPrjRelation" fetch="join">
        	<key column="BranchID"></key>
        	<many-to-many class="org.tbcc.entity.TbccPrjType" column="ProjectID"></many-to-many>
        </set>
        
        
        <property name="branchDisplayName" type="java.lang.String" column="branchDisplayName"></property>
        <property name="branchLogo" type="java.sql.Blob" column="branchLogo"></property>
        <property name="branchLogoEnable" type="java.lang.Integer" column="branchLogoEnable"></property>
        
    </class>
</hibernate-mapping>
